pylampo_client/__init__.py
pylampo_client/client.py
pylampo_client/deamon.py
pylampo_client-0.0.5.dist-info/METADATA
pylampo_client-0.0.5.dist-info/WHEEL
pylampo_client-0.0.5.dist-info/RECORD
