Metadata-Version: 2.1
Name: pylampo-client
Version: 0.0.5
Summary: A simple Lampo client that communicates via Rest API, and provide utils to run lampod
Author: Tarek
Author-email: tareknaser360@gmail.com
Requires-Python: >=3.8,<4.0
Classifier: Programming Language :: Python :: 3
Classifier: Programming Language :: Python :: 3.8
Classifier: Programming Language :: Python :: 3.9
Classifier: Programming Language :: Python :: 3.10
Classifier: Programming Language :: Python :: 3.11
Classifier: Programming Language :: Python :: 3.12
Classifier: Programming Language :: Python :: 3.13
Requires-Dist: requests (>=2.32.3,<3.0.0)
